coloring_py/__init__.py
coloring_py/coloring.py
coloring_py-0.5.dist-info/METADATA
coloring_py-0.5.dist-info/WHEEL
coloring_py-0.5.dist-info/top_level.txt
coloring_py-0.5.dist-info/RECORD
